wiggler/__init__.py
wiggler/cli.py
wiggler/main.py
wiggler/display/__init__.py
wiggler/display/auto_slider.py
wiggler/display/pot_slider.py
wiggler/light/__init__.py
wiggler/light/pixels.py
wiggler/service/wiggler.service
wiggler/service/wiggler_boot.sh
wiggler_studiorabota-0.0.46.dist-info/METADATA
wiggler_studiorabota-0.0.46.dist-info/WHEEL
wiggler_studiorabota-0.0.46.dist-info/entry_points.txt
wiggler_studiorabota-0.0.46.dist-info/top_level.txt
wiggler_studiorabota-0.0.46.dist-info/RECORD
